rmlst_cli/__init__.py
rmlst_cli/_version.py
rmlst_cli/api.py
rmlst_cli/cli.py
rmlst_cli/fasta.py
rmlst_cli/formats.py
rmlst_cli/http.py
rmlst_cli/io.py
rmlst_cli-1.0.dist-info/METADATA
rmlst_cli-1.0.dist-info/WHEEL
rmlst_cli-1.0.dist-info/entry_points.txt
rmlst_cli-1.0.dist-info/licenses/LICENSE
rmlst_cli-1.0.dist-info/RECORD
