Metadata-Version: 2.4
Name: rmlst-cli
Version: 1.0
Summary: rmlst-cli is a simple tool to use the rMLST API through the command line.
Project-URL: Homepage, https://github.com/ssi-dk/rmlst_cli
Project-URL: Source, https://github.com/ssi-dk/rmlst_cli
Project-URL: Issues, https://github.com/ssi-dk/rmlst_cli/issues
Author-email: Povilas Matusevicius <pmat@ssi.dk>
Maintainer-email: Povilas Matusevicius <pmat@ssi.dk>
License-Expression: MIT
License-File: LICENSE
Requires-Python: <3.15,>=3.9
Requires-Dist: biopython
Requires-Dist: click
Requires-Dist: requests
